README.txt
setup.py
collective/__init__.py
collective.eventinviter.egg-info/PKG-INFO
collective.eventinviter.egg-info/SOURCES.txt
collective.eventinviter.egg-info/dependency_links.txt
collective.eventinviter.egg-info/entry_points.txt
collective.eventinviter.egg-info/namespace_packages.txt
collective.eventinviter.egg-info/not-zip-safe
collective.eventinviter.egg-info/paster_plugins.txt
collective.eventinviter.egg-info/requires.txt
collective.eventinviter.egg-info/top_level.txt
collective/eventinviter/__init__.py
collective/eventinviter/attendees.py
collective/eventinviter/configure.zcml
collective/eventinviter/interfaces.py
collective/eventinviter/inviter.py
collective/eventinviter/todo.txt
collective/eventinviter/locales/collective.eventinviter.pot
collective/eventinviter/locales/pt/LC_MESSAGES/collective.eventinviter.po
collective/eventinviter/tests/__init__.py
collective/eventinviter/tests/common.py
collective/eventinviter/tests/inviter.txt
collective/eventinviter/tests/test_inviter.py
docs/HISTORY.txt
docs/INSTALL.txt
docs/LICENSE.GPL
docs/LICENSE.txt
