Metadata-Version: 1.0
Name: collective.eventinviter
Version: 0.1b1
Summary: Event Inviter
Home-page: http://svn.plone.org/svn/collective/collective.eventinviter
Author: Ricardo Alves
Author-email: rsa@eurotux.com
License: GPL
Keywords: plone event ical invitation
Platform: UNKNOWN
Classifier: Framework :: Plone
Classifier: Programming Language :: Python
Classifier: Topic :: Software Development :: Libraries :: Python Modules
